LICENSE
MANIFEST.in
README.rst
setup.py
hn/__init__.py
hn/core.py
hn/hnapi.py
pyhackernews.egg-info/PKG-INFO
pyhackernews.egg-info/SOURCES.txt
pyhackernews.egg-info/dependency_links.txt
pyhackernews.egg-info/entry_points.txt
pyhackernews.egg-info/requires.txt
pyhackernews.egg-info/top_level.txt