Metadata-Version: 1.1
Name: pyhackernews
Version: 0.1
Summary: mimicking HN look and feel in terminal
Home-page: https://github.com/danclaudiupop/hackernews/
Author: Dan Claudiu Pop
Author-email: dancladiupop@gmail.com
License: The MIT License (MIT)
